{"actStorage":[{"actual":0,"month":1,"year":2012},{"actual":0,"month":2,"year":2012},{"actual":0,"month":3,"year":2012},{"actual":0,"month":4,"year":2012},{"actual":0,"month":5,"year":2012},{"actual":18949505,"month":6,"year":2012},{"actual":12849917,"month":7,"year":2012},{"actual":13342068,"month":8,"year":2012},{"actual":13293937,"month":9,"year":2012},{"actual":12437344,"month":10,"year":2012},{"actual":10347482,"month":11,"year":2012},{"actual":10061782,"month":12,"year":2012}],"name":"国网天津电力滨海仓库","no":"BGCA","norminalStorage":[{"max":10000000,"norminal":9000000,"year":2012}]}