{"actStorage":[{"actual":0,"month":1,"year":2012},{"actual":0,"month":2,"year":2012},{"actual":0,"month":3,"year":2012},{"actual":0,"month":4,"year":2012},{"actual":0,"month":5,"year":2012},{"actual":12646642,"month":6,"year":2012},{"actual":2067032,"month":7,"year":2012},{"actual":2040993,"month":8,"year":2012},{"actual":1992049,"month":9,"year":2012},{"actual":1992049,"month":10,"year":2012},{"actual":1992049,"month":11,"year":2012},{"actual":1992049,"month":12,"year":2012},{"actual":1992049,"month":1,"year":2013},{"actual":1992049,"month":2,"year":2013},{"actual":1992049,"month":3,"year":2013},{"actual":1992049,"month":4,"year":2013},{"actual":1918244,"month":5,"year":2013},{"actual":1273151,"month":6,"year":2013},{"actual":864468,"month":7,"year":2013},{"actual":731646,"month":8,"year":2013},{"actual":671566,"month":9,"year":2013},{"actual":671449,"month":10,"year":2013},{"actual":633976,"month":11,"year":2013},{"actual":322811,"month":12,"year":2013},{"actual":322811,"month":1,"year":2014},{"actual":432811,"month":2,"year":2014},{"actual":432811,"month":3,"year":2014},{"actual":427208,"month":4,"year":2014},{"actual":512400,"month":5,"year":2014},{"actual":635477,"month":6,"year":2014},{"actual":1557124,"month":7,"year":2014},{"actual":0,"month":8,"year":2014},{"actual":0,"month":9,"year":2014},{"actual":0,"month":10,"year":2014},{"actual":0,"month":11,"year":2014},{"actual":0,"month":12,"year":2014}],"name":"国网天津电力蓟县仓库","no":"BHCA","norminalStorage":[{"max":14000000,"norminal":10000000,"year":2012},{"max":15000000,"norminal":11000000,"year":2010},{"max":12000000,"norminal":10000000,"year":2011},{"max":13000000,"norminal":11000000,"year":2013},{"max":14000000,"norminal":12000000,"year":2014}]}